Lightflow_Rest-1.1.0.dist-info/DESCRIPTION.rst
Lightflow_Rest-1.1.0.dist-info/METADATA
Lightflow_Rest-1.1.0.dist-info/RECORD
Lightflow_Rest-1.1.0.dist-info/WHEEL
Lightflow_Rest-1.1.0.dist-info/metadata.json
Lightflow_Rest-1.1.0.dist-info/top_level.txt
lightflow_rest/__init__.py
lightflow_rest/service.py
lightflow_rest/api/__init__.py
lightflow_rest/api/config.py
lightflow_rest/api/worker.py
lightflow_rest/api/workflow.py
lightflow_rest/core/__init__.py
lightflow_rest/core/app.py
lightflow_rest/core/response.py
