Metadata-Version: 2.0
Name: Lightflow-Rest
Version: 1.1.0
Summary: A REST extension for Lightflow.
Home-page: https://bitbucket.synchrotron.org.au/projects/DR/repos/lightflow-rest/browse
Author: The Australian Synchrotron Python Group
Author-email: python@synchrotron.org.au
License: UNKNOWN
Platform: UNKNOWN
Classifier: Development Status :: 3 - Alpha
Classifier: Topic :: Scientific/Engineering
Classifier: Intended Audience :: Developers
Classifier: Intended Audience :: Science/Research
Classifier: Natural Language :: English
Classifier: Intended Audience :: Developers
Classifier: Programming Language :: Python :: 3
Classifier: Programming Language :: Python :: 3.5
Requires-Dist: lightflow (>=1.2.4)
Requires-Dist: Flask (>=0.12.1)
Requires-Dist: ruamel.yaml (>=0.14.2)
